ethereum/__init__.py
ethereum/core/__init__.py
ethereum/core/__init__.pyi
ethereum/core/exc.py
ethereum/core/util.py
ethereum/core/validation.py
ethereum/core/http/__init__.py
ethereum/core/http/__init__.pyi
ethereum/core/http/client.py
ethereum/etherscan/__init__.py
ethereum/etherscan/__init__.pyi
ethereum/etherscan/_etherscan.py
ethereum/etherscan/block_by_time.py
ethereum/etherscan/token_transactions.py
ethereum/etherscan/transaction_by_hash.py
ethereum/etherscan/transactions.py
ethereum/etherscan/core/__init__.py
ethereum/etherscan/core/auth.py
ethereum/etherscan/core/mixin.py
ethereum/etherscan/core/types.py
ethereum/node_rpc/__init__.py
ethereum/node_rpc/__init__.pyi
ethereum/node_rpc/_node_rpc.py
ethereum/node_rpc/core.py
ethereum/node_rpc/eth_balance.py
ethereum/node_rpc/token_balance.py
ethereum/sdk/__init__.py
ethereum/sdk/__init__.pyi
ethereum/sdk/snapshots.py
ethereum/sdk/transactions.py
ethereum/sdk/core/__init__.py
ethereum/sdk/core/__init__.pyi
ethereum/sdk/core/etherscan.py
ethereum/sdk/core/rpc.py
ethereum_trading_sdk-0.1.1.dist-info/METADATA
ethereum_trading_sdk-0.1.1.dist-info/WHEEL
ethereum_trading_sdk-0.1.1.dist-info/top_level.txt
ethereum_trading_sdk-0.1.1.dist-info/RECORD
