Metadata-Version: 2.4
Name: ethereum-trading-sdk
Version: 0.1.1
Summary: Typed Python SDK for Ethereum
Author-email: Marcel Claramunt <marcel@tribulnation.com>
Requires-Python: >=3.10
Requires-Dist: web3
Requires-Dist: httpx
Requires-Dist: pydantic
